LICENSE
README.md
setup.cfg
setup.py
fmperf/Cluster.py
fmperf/ModelSpecs.py
fmperf/WorkloadSpecs.py
fmperf/__init__.py
fmperf.egg-info/PKG-INFO
fmperf.egg-info/SOURCES.txt
fmperf.egg-info/dependency_links.txt
fmperf.egg-info/requires.txt
fmperf.egg-info/top_level.txt
fmperf/data/__init__.py
fmperf/data/ai.txt
fmperf/data/all_nbins_64.pkl
fmperf/loadgen/__init__.py
fmperf/loadgen/collect_energy.py
fmperf/loadgen/custom_histogram_model.py
fmperf/loadgen/generate-input.py
fmperf/loadgen/generate-text-from-quac.py
fmperf/loadgen/run.py
fmperf/loadgen/sweep.py
fmperf/loadgen/test_collect_energy.py
fmperf/utils/Benchmarking.py
fmperf/utils/Creating.py
fmperf/utils/Deleting.py
fmperf/utils/Logging.py
fmperf/utils/Parsing.py
fmperf/utils/Waiting.py
fmperf/utils/__init__.py